MANIFEST.in
README.txt
setup.py
collective/__init__.py
collective.blog.portlets.egg-info/PKG-INFO
collective.blog.portlets.egg-info/SOURCES.txt
collective.blog.portlets.egg-info/dependency_links.txt
collective.blog.portlets.egg-info/entry_points.txt
collective.blog.portlets.egg-info/namespace_packages.txt
collective.blog.portlets.egg-info/not-zip-safe
collective.blog.portlets.egg-info/requires.txt
collective.blog.portlets.egg-info/top_level.txt
collective/blog/__init__.py
collective/blog/portlets/__init__.py
collective/blog/portlets/archive.pt
collective/blog/portlets/archive.py
collective/blog/portlets/configure.zcml
collective/blog/portlets/last_entries.pt
collective/blog/portlets/last_entries.py
collective/blog/portlets/rebuild_i18n.sh
collective/blog/portlets/tests.py
collective/blog/portlets/utils.py
collective/blog/portlets/version.txt
collective/blog/portlets/locales/collective.blog.portlets-manual.pot
collective/blog/portlets/locales/collective.blog.portlets.pot
collective/blog/portlets/locales/plone.pot
collective/blog/portlets/locales/de/LC_MESSAGES/collective.blog.portlets.po
collective/blog/portlets/locales/de/LC_MESSAGES/plone.po
collective/blog/portlets/locales/en/LC_MESSAGES/collective.blog.portlets.po
collective/blog/portlets/locales/es/LC_MESSAGES/collective.blog.portlets.po
collective/blog/portlets/locales/es/LC_MESSAGES/plone.po
collective/blog/portlets/locales/eu/LC_MESSAGES/collective.blog.portlets.po
collective/blog/portlets/locales/eu/LC_MESSAGES/plone.po
collective/blog/portlets/locales/fr/LC_MESSAGES/collective.blog.portlets.po
collective/blog/portlets/locales/fr/LC_MESSAGES/plone.po
collective/blog/portlets/locales/it/LC_MESSAGES/collective.blog.portlets.po
collective/blog/portlets/locales/it/LC_MESSAGES/plone.po
collective/blog/portlets/locales/nl/LC_MESSAGES/collective.blog.portlets.po
collective/blog/portlets/locales/nl/LC_MESSAGES/plone.po
collective/blog/portlets/locales/no/LC_MESSAGES/collective.blog.portlets.po
collective/blog/portlets/locales/no/LC_MESSAGES/plone.po
collective/blog/portlets/locales/pt-br/LC_MESSAGES/collective.blog.portlets.po
collective/blog/portlets/locales/pt-br/LC_MESSAGES/plone.po
collective/blog/portlets/profiles/default/metadata.xml
collective/blog/portlets/profiles/default/portlets.xml
docs/HISTORY.txt
docs/INSTALL.txt
docs/LICENSE.GPL
docs/LICENSE.txt