Metadata-Version: 1.0
Name: collective.blog.portlets
Version: 1.6
Summary: Archive view and portlet
Home-page: http://github.com/collective/collective.blog.portlets
Author: Jarn AS
Author-email: info@jarn.com
License: GPL
Keywords: plone blog portlet archive
Platform: UNKNOWN
Classifier: Framework :: Plone
Classifier: Framework :: Plone :: 4.0
Classifier: Framework :: Plone :: 4.1
Classifier: Framework :: Plone :: 4.2
Classifier: Framework :: Plone :: 4.3
Classifier: Programming Language :: Python
Classifier: Programming Language :: Python :: 2.6
Classifier: Programming Language :: Python :: 2.7
